st_card_component/__init__.py
st_card_component/frontend/build/asset-manifest.json
st_card_component/frontend/build/bootstrap.min.css
st_card_component/frontend/build/index.html
st_card_component/frontend/build/precache-manifest.9da28e869bd47029a54a1f36a791753f.js
st_card_component/frontend/build/service-worker.js
st_card_component/frontend/build/static/js/2.cefea37b.chunk.js
st_card_component/frontend/build/static/js/2.cefea37b.chunk.js.LICENSE.txt
st_card_component/frontend/build/static/js/2.cefea37b.chunk.js.map
st_card_component/frontend/build/static/js/main.7d4bcb1d.chunk.js
st_card_component/frontend/build/static/js/main.7d4bcb1d.chunk.js.map
st_card_component/frontend/build/static/js/runtime-main.c6b6296f.js
st_card_component/frontend/build/static/js/runtime-main.c6b6296f.js.map
st_card_component_alex-0.0.1.dist-info/LICENSE
st_card_component_alex-0.0.1.dist-info/METADATA
st_card_component_alex-0.0.1.dist-info/WHEEL
st_card_component_alex-0.0.1.dist-info/top_level.txt
st_card_component_alex-0.0.1.dist-info/RECORD
